gf2lib/__init__.py
gf2lib/gf2matrix.py
gf2lib/gf2poly.py
gf2lib-0.0.1.dist-info/METADATA
gf2lib-0.0.1.dist-info/WHEEL
gf2lib-0.0.1.dist-info/licenses/LICENSE
gf2lib-0.0.1.dist-info/RECORD
