Metadata-Version: 2.1
Name: gf2lib
Version: 0.0.1
Summary: gf2lib is a library for manipulating GF (2) polynomials and GF (2) matrices over finite fields
Project-URL: Homepage, https://github.com/oldprincess/gf2lib
Project-URL: Bug Tracker, https://github.com/oldprincess/gf2lib/issues
Author-email: oldprincess <zirui.gong@foxmail.com>
License-File: LICENSE
Classifier: License :: OSI Approved :: BSD License
Classifier: Operating System :: OS Independent
Classifier: Programming Language :: Python :: 3
Requires-Python: >=3.7
